psplines/__init__.py
psplines/basis.py
psplines/core.py
psplines/optimize.py
psplines/penalty.py
psplines/setup.py
psplines/utils.py
psplines/utils_math.py
psplines-0.1.3.dist-info/METADATA
psplines-0.1.3.dist-info/WHEEL
psplines-0.1.3.dist-info/entry_points.txt
psplines-0.1.3.dist-info/licenses/LICENSE
psplines-0.1.3.dist-info/RECORD
