Metadata-Version: 2.4
Name: psplines
Version: 0.1.3
Summary: Implementation of PSplines in Python
Author-email: Grayson Bellamy <graysontbellamy@gmail.com>
License-File: LICENSE
Requires-Python: >=3.10
Requires-Dist: arviz
Requires-Dist: matplotlib
Requires-Dist: numpy
Requires-Dist: pymc
Requires-Dist: pytensor
Requires-Dist: scipy
